ppgs/__init__.py
ppgs/__main__.py
ppgs/core.py
ppgs/load.py
ppgs/phonemes.py
ppgs/assets/balanced_similarity.pt
ppgs/assets/phoneme_weights.pt
ppgs/assets/configs/bottleneck.yaml
ppgs/assets/configs/ppg-quality-mushra.yaml
ppgs/assets/partitions/arctic.json
ppgs/assets/partitions/commonvoice.json
ppgs/assets/partitions/timit.json
ppgs/config/__init__.py
ppgs/config/defaults.py
ppgs/config/static.py
ppgs/config/w2v2fb.py
ppgs/data/__init__.py
ppgs/data/collate.py
ppgs/data/dataset.py
ppgs/data/loader.py
ppgs/data/sampler.py
ppgs/data/datasets/__init__.py
ppgs/data/datasets/arctic/__init__.py
ppgs/data/datasets/arctic/core.py
ppgs/data/datasets/arctic/words/__init__.py
ppgs/data/datasets/arctic/words/align.py
ppgs/data/datasets/arctic/words/core.py
ppgs/data/datasets/commonvoice/__init__.py
ppgs/data/datasets/commonvoice/core.py
ppgs/data/datasets/timit/__init__.py
ppgs/data/datasets/timit/core.py
ppgs/data/download/__init__.py
ppgs/data/download/__main__.py
ppgs/data/download/core.py
ppgs/data/download/align/__init__.py
ppgs/data/download/align/core.py
ppgs/data/stats/__init__.py
ppgs/data/stats/__main__.py
ppgs/data/stats/core.py
ppgs/edit/__init__.py
ppgs/edit/core.py
ppgs/edit/grid.py
ppgs/evaluate/__init__.py
ppgs/evaluate/__main__.py
ppgs/evaluate/core.py
ppgs/evaluate/metrics.py
ppgs/evaluate/visualize.py
ppgs/model/__init__.py
ppgs/model/convolution.py
ppgs/model/core.py
ppgs/model/transformer.py
ppgs/model/w2v2.py
ppgs/model/w2v2fc.py
ppgs/partition/__init__.py
ppgs/partition/__main__.py
ppgs/partition/core.py
ppgs/plot/__init__.py
ppgs/plot/__main__.py
ppgs/plot/core.py
ppgs/plot/accuracy/__init__.py
ppgs/plot/accuracy/__main__.py
ppgs/plot/accuracy/core.py
ppgs/preprocess/__init__.py
ppgs/preprocess/__main__.py
ppgs/preprocess/core.py
ppgs/preprocess/dac.py
ppgs/preprocess/encodec.py
ppgs/preprocess/mel.py
ppgs/preprocess/spectrogram.py
ppgs/preprocess/bottleneck/__init__.py
ppgs/preprocess/bottleneck/core.py
ppgs-0.0.9.dist-info/LICENSE
ppgs-0.0.9.dist-info/METADATA
ppgs-0.0.9.dist-info/WHEEL
ppgs-0.0.9.dist-info/top_level.txt
ppgs-0.0.9.dist-info/RECORD
