Metadata-Version: 2.2
Name: ppgs
Version: 0.0.9
Summary: Phonetic posteriorgrams
Home-page: https://github.com/interactiveaudiolab/ppgs
Author: Interactive Audio Lab
Author-email: interactiveaudiolab@gmail.com
License: MIT
Keywords: phonemes,ppg,pronunciation,speech
Classifier: License :: OSI Approved :: MIT License
License-File: LICENSE
Requires-Dist: espnet
Requires-Dist: huggingface-hub
Requires-Dist: librosa
Requires-Dist: matplotlib
Requires-Dist: moviepy>=2.0.0
Requires-Dist: numpy
Requires-Dist: pypar
Requires-Dist: torch
Requires-Dist: torchaudio
Requires-Dist: torchutil
Requires-Dist: tqdm
Requires-Dist: transformers
Requires-Dist: opencv-python
Requires-Dist: yapecs
Provides-Extra: train
Requires-Dist: dac; extra == "train"
Requires-Dist: encodec; extra == "train"
Requires-Dist: g2pM; extra == "train"
Requires-Dist: gdown>=4.6.2; extra == "train"
Requires-Dist: humanfriendly; extra == "train"
Requires-Dist: nltk; extra == "train"
Requires-Dist: pyyaml; extra == "train"
Requires-Dist: torch-complex; extra == "train"
Dynamic: author
Dynamic: author-email
Dynamic: classifier
Dynamic: description
Dynamic: description-content-type
Dynamic: home-page
Dynamic: keywords
Dynamic: license
Dynamic: provides-extra
Dynamic: requires-dist
Dynamic: summary
